{"features":[{"geometry":{"coordinates":[-90.9465119363536,38.54799980362421],"type":"Point"},"metadata":{"DeviceID":"Administrator","LastUpdated":"2021-11-17T13:16:17.012Z","MUID_G":"8c196f28-9b90-4b84-b292-c3b53f3ff8ae","XLong":"-90.9465119363536","YLat":"38.54799980362421"},"properties":{"__action":"upsert","__draw":"0","__dynamic":"0","__feature":"User Feature","__form":"sysMainRepairs","__form_id":"030938b6-92c1-4d99-bccb-7ed117ce5a43","__history":"0","__id":"8c196f28-9b90-4b84-b292-c3b53f3ff8ae","__insert_id":"8c196f28-9b90-4b84-b292-c3b53f3ff8ae","__latitude":38.54799980362421,"__layer_types":"0","__layers":"92b07314-ae63-4293-b889-697b104e72e0_2e1e9299-5c40-4fb9-978f-188ce91dd3c0","__longitude":-90.9465119363536,"__map":"Franklin Co Cloud","__map_id":"374176c5-bbcb-42bd-bea5-b1c7a01772aa","__user":"Administrator","__user_id":"admin","__version":"e36115e9-9ab0-4a0a-89d6-94a6c99c39c9","comment":"ASDF","description":"ASDF","division":"water","location":"ASDF","material":"ASDF","purpose":"SADF","repaired":"2021-11-17","repairedby":"ASDF","size":"ASDF"},"type":"Feature"},{"geometry":{"coordinates":[-90.85096160160175,38.480342809985814],"type":"Point"},"metadata":{"DeviceID":"Franklin Co Editor","LastUpdated":"2021-11-17T14:17:17.622Z","MUID_G":"d22e269d-b7a7-44f1-a14a-25eb92b6241d","XLong":"-90.85096160160175","YLat":"38.480342809985814","accuracy":"1.37"},"properties":{"__action":"upsert","__draw":"0","__dynamic":"0","__feature":"New Feature","__form":"sysMainRepairs","__form_id":"030938b6-92c1-4d99-bccb-7ed117ce5a43","__history":"0","__id":"d22e269d-b7a7-44f1-a14a-25eb92b6241d","__insert_id":"d22e269d-b7a7-44f1-a14a-25eb92b6241d","__latitude":38.480342809985814,"__layer_types":"0","__layers":"92b07314-ae63-4293-b889-697b104e72e0_2e1e9299-5c40-4fb9-978f-188ce91dd3c0","__longitude":-90.85096160160175,"__map":"Franklin Co Cloud","__map_id":"374176c5-bbcb-42bd-bea5-b1c7a01772aa","__user":"Franklin Co Editor","__user_id":"franklinedit","__version":"f69d09e1-4ac0-4be9-9ff4-880c066803ae","comment":"6’ section","division":"water","location":"By Colman School","material":"Two top bolts","purpose":"Boring company hit main","repaired":"2021-11-16","repairedby":"Alliance Water Resources","size":"10"},"type":"Feature"}],"type":"FeatureCollection"}